{"nodes": {"0": {"node_name": "cloudInstance_0", "node_type": "cloudInstance", "cpu_availability": 5.0, "memory_availability": 1024.0, "bandwidth": 62.5, "bandwidth_usage": 82.5, "layer": "cloud"}, "1": {"node_name": "edgeNode-a_1", "node_type": "edgeNode-a", "cpu_availability": 2, "memory_availability": 4096.0, "bandwidth": 25.0, "bandwidth_usage": 20.0, "layer": "edge"}, "2": {"node_name": "edgeNode-b_2", "node_type": "edgeNode-b", "cpu_availability": 2, "memory_availability": 2048.0, "bandwidth": 25.0, "bandwidth_usage": 25.0, "layer": "edge"}, "3": {"node_name": "client_3", "node_type": "client", "cpu_availability": 15.0, "memory_availability": 15360.0, "bandwidth": 25.0, "bandwidth_usage": 20.0, "layer": "client"}}, "microservices": {"iot-ms-app": {"instances": {"0": {"node_id": 3, "cpu_requests": 1.0, "memory_requests": 1024.0, "total_bandwidth": 20.0}, "1": {"node_id": 0, "cpu_requests": 1.0, "memory_requests": 1024.0, "total_bandwidth": 20.0}, "2": {"node_id": 0, "cpu_requests": 1.0, "memory_requests": 1024.0, "total_bandwidth": 0}, "3": {"node_id": 0, "cpu_requests": 1.0, "memory_requests": 1024.0, "total_bandwidth": 0}}}}}